edwh_whitelabel_plugin/__about__.py
edwh_whitelabel_plugin/__init__.py
edwh_whitelabel_plugin/whitelabel_plugin.py
edwh_whitelabel_plugin-0.1.2.dist-info/METADATA
edwh_whitelabel_plugin-0.1.2.dist-info/WHEEL
edwh_whitelabel_plugin-0.1.2.dist-info/entry_points.txt
edwh_whitelabel_plugin-0.1.2.dist-info/licenses/LICENSE.txt
edwh_whitelabel_plugin-0.1.2.dist-info/RECORD
